swagger_ui_bundle/__init__.py
swagger_ui_bundle/vendor/swagger-ui-5.31.0/favicon-16x16.png
swagger_ui_bundle/vendor/swagger-ui-5.31.0/favicon-32x32.png
swagger_ui_bundle/vendor/swagger-ui-5.31.0/index.css
swagger_ui_bundle/vendor/swagger-ui-5.31.0/index.html
swagger_ui_bundle/vendor/swagger-ui-5.31.0/index.j2
swagger_ui_bundle/vendor/swagger-ui-5.31.0/oauth2-redirect.html
swagger_ui_bundle/vendor/swagger-ui-5.31.0/oauth2-redirect.js
swagger_ui_bundle/vendor/swagger-ui-5.31.0/swagger-initializer.js
swagger_ui_bundle/vendor/swagger-ui-5.31.0/swagger-ui-bundle.js
swagger_ui_bundle/vendor/swagger-ui-5.31.0/swagger-ui-bundle.js.map
swagger_ui_bundle/vendor/swagger-ui-5.31.0/swagger-ui-es-bundle-core.js
swagger_ui_bundle/vendor/swagger-ui-5.31.0/swagger-ui-es-bundle-core.js.map
swagger_ui_bundle/vendor/swagger-ui-5.31.0/swagger-ui-es-bundle.js
swagger_ui_bundle/vendor/swagger-ui-5.31.0/swagger-ui-es-bundle.js.map
swagger_ui_bundle/vendor/swagger-ui-5.31.0/swagger-ui-standalone-preset.js
swagger_ui_bundle/vendor/swagger-ui-5.31.0/swagger-ui-standalone-preset.js.map
swagger_ui_bundle/vendor/swagger-ui-5.31.0/swagger-ui.css
swagger_ui_bundle/vendor/swagger-ui-5.31.0/swagger-ui.css.map
swagger_ui_bundle/vendor/swagger-ui-5.31.0/swagger-ui.js
swagger_ui_bundle/vendor/swagger-ui-5.31.0/swagger-ui.js.map
swagger_ui_bundle_v2-5.31.0.dist-info/METADATA
swagger_ui_bundle_v2-5.31.0.dist-info/WHEEL
swagger_ui_bundle_v2-5.31.0.dist-info/licenses/LICENSE
swagger_ui_bundle_v2-5.31.0.dist-info/RECORD
