Metadata-Version: 2.4
Name: swagger-ui-bundle-v2
Version: 5.31.0
Summary: Swagger UI bundled for usage with Python
License: Apache-2.0
License-File: LICENSE
Keywords: swagger-ui
Author: Daniel Grossmann-Kavanagh
Maintainer: Robbe Sneyders
Maintainer-email: robbe.sneyders@gmail.com
Requires-Python: >=3.9
Classifier: Development Status :: 5 - Production/Stable
Classifier: Intended Audience :: Developers
Classifier: License :: OSI Approved :: Apache Software License
Classifier: Operating System :: OS Independent
Classifier: Programming Language :: Python
Classifier: Programming Language :: Python :: 3
Classifier: Programming Language :: Python :: 3.9
Classifier: Programming Language :: Python :: 3.10
Classifier: Programming Language :: Python :: 3.11
Classifier: Programming Language :: Python :: 3.12
Classifier: Programming Language :: Python :: 3.13
Classifier: Programming Language :: Python :: 3.14
Classifier: Programming Language :: Python :: 3 :: Only
Classifier: Topic :: Internet
Classifier: Topic :: Internet :: WWW/HTTP
Classifier: Topic :: Internet :: WWW/HTTP :: HTTP Servers
Classifier: Topic :: Software Development
Classifier: Topic :: Software Development :: Libraries
Classifier: Topic :: Software Development :: Libraries :: Python Modules
Classifier: Typing :: Typed
Requires-Dist: Jinja2 (>=3.0.0,<4.0.0)
Project-URL: Repository, https://github.com/spec-first/swagger_ui_bundle
